flamp/__init__.py
flamp/array.py
flamp/eigen.py
flamp/eigen_symmetric.py
flamp/linalg.py
flamp-1.0.1.dist-info/LICENSE
flamp-1.0.1.dist-info/METADATA
flamp-1.0.1.dist-info/WHEEL
flamp-1.0.1.dist-info/top_level.txt
flamp-1.0.1.dist-info/RECORD
