Metadata-Version: 2.1
Name: flamp
Version: 1.0.1
Summary: Faster linear algebra with multiple precision
Home-page: https://github.com/c-f-h/flamp
Author: Clemens Hofreither
Author-email: clemens.hofreither@ricam.oeaw.ac.at
License: UNKNOWN
Platform: UNKNOWN
Classifier: Programming Language :: Python :: 3
Classifier: Intended Audience :: Science/Research
Classifier: Topic :: Scientific/Engineering :: Mathematics
Classifier: License :: OSI Approved :: BSD License
License-File: LICENSE
